<?xml version="1.0" encoding="utf-8"?>
<SaveFile xmlns:xsi="http://www.w3.org/2001/XMLSchema-instance" xmlns:xsd="http://www.w3.org/2001/XMLSchema">
  <saveString>
    <string />
  </saveString>
  <saveType>
    <ItemSaveType>
      <type>0</type>
      <_amount>0</_amount>
    </ItemSaveType>
    <ItemSaveType>
      <type>0</type>
      <_amount>0</_amount>
    </ItemSaveType>
    <ItemSaveType>
      <type>0</type>
      <_amount>0</_amount>
    </ItemSaveType>
    <ItemSaveType>
      <type>0</type>
      <_amount>0</_amount>
    </ItemSaveType>
    <ItemSaveType>
      <type>0</type>
      <_amount>0</_amount>
    </ItemSaveType>
    <ItemSaveType>
      <type>0</type>
      <_amount>0</_amount>
    </ItemSaveType>
    <ItemSaveType>
      <type>0</type>
      <_amount>0</_amount>
    </ItemSaveType>
    <ItemSaveType>
      <type>0</type>
      <_amount>0</_amount>
    </ItemSaveType>
    <ItemSaveType>
      <type>0</type>
      <_amount>0</_amount>
    </ItemSaveType>
    <ItemSaveType>
      <type>0</type>
      <_amount>0</_amount>
    </ItemSaveType>
    <ItemSaveType>
      <type>0</type>
      <_amount>0</_amount>
    </ItemSaveType>
    <ItemSaveType>
      <type>0</type>
      <_amount>0</_amount>
    </ItemSaveType>
    <ItemSaveType>
      <type>0</type>
      <_amount>0</_amount>
    </ItemSaveType>
    <ItemSaveType>
      <type>0</type>
      <_amount>0</_amount>
    </ItemSaveType>
    <ItemSaveType>
      <type>0</type>
      <_amount>0</_amount>
    </ItemSaveType>
    <ItemSaveType>
      <type>0</type>
      <_amount>0</_amount>
    </ItemSaveType>
    <ItemSaveType>
      <type>0</type>
      <_amount>0</_amount>
    </ItemSaveType>
    <ItemSaveType>
      <type>0</type>
      <_amount>0</_amount>
    </ItemSaveType>
    <ItemSaveType>
      <type>0</type>
      <_amount>0</_amount>
    </ItemSaveType>
    <ItemSaveType>
      <type>0</type>
      <_amount>0</_amount>
    </ItemSaveType>
    <ItemSaveType>
      <type>0</type>
      <_amount>0</_amount>
    </ItemSaveType>
    <ItemSaveType>
      <type>0</type>
      <_amount>0</_amount>
    </ItemSaveType>
    <ItemSaveType>
      <type>0</type>
      <_amount>0</_amount>
    </ItemSaveType>
    <ItemSaveType>
      <type>0</type>
      <_amount>0</_amount>
    </ItemSaveType>
    <ItemSaveType>
      <type>0</type>
      <_amount>0</_amount>
    </ItemSaveType>
    <ItemSaveType>
      <type>0</type>
      <_amount>0</_amount>
    </ItemSaveType>
    <ItemSaveType>
      <type>0</type>
      <_amount>0</_amount>
    </ItemSaveType>
    <ItemSaveType>
      <type>0</type>
      <_amount>0</_amount>
    </ItemSaveType>
    <ItemSaveType>
      <type>0</type>
      <_amount>0</_amount>
    </ItemSaveType>
    <ItemSaveType>
      <type>0</type>
      <_amount>0</_amount>
    </ItemSaveType>
  </saveType>
  <biomeItemSave>
    <string>1</string>
  </biomeItemSave>
  <worldItemSave>
    <WorldItemSave>
      <type />
      <pos />
    </WorldItemSave>
  </worldItemSave>
  <playerPos>
    <x>554.185852</x>
    <y>1.04999626</y>
    <z>2118.54443</z>
  </playerPos>
  <playerValues>
    <health>0</health>
    <hunger>99</hunger>
    <thirst>78</thirst>
    <fatigue>99.72994</fatigue>
    <temperature>22.82775</temperature>
  </playerValues>
  <TimeOfDay>14.1553144</TimeOfDay>
  <Temperature>14.1553144</Temperature>
  <TempAdjust>0</TempAdjust>
</SaveFile>